[
    {
        "": "0",
        "Species": "Carbon Dioxide",
        "Industrial": "73940.00674894094",
        "Onroad Transportation": "323689.54341164755",
        "Power": "153317.6646341048",
        "Nonroad Transportation": "25089.411798657326",
        "Other": "0.0",
        "Residential + Commercial": "47217.647758237144",
        "Industrial Percent of Total": "5.931768925666232",
        "Onroad Transportation Percent of Total": "25.967695427615077",
        "Power Percent of Total": "12.299768404407477",
        "Nonroad Transportation Percent of Total": "2.012774948423316",
        "Other Percent of Total": "0.0",
        "Residential + Commercial Percent of Total": "3.7879922930812633"
    },
    {
        "": "1",
        "Species": "Carbon Monoxide",
        "Industrial": "209.35106929207737",
        "Onroad Transportation": "1194.9106767992337",
        "Power": "15.803252427413355",
        "Nonroad Transportation": "1165.051715053402",
        "Other": "0.0",
        "Residential + Commercial": "310.5992101583414",
        "Industrial Percent of Total": "3.614841313807781",
        "Onroad Transportation Percent of Total": "20.6323879567944",
        "Power Percent of Total": "0.2728729782003018",
        "Nonroad Transportation Percent of Total": "20.11681663026035",
        "Other Percent of Total": "0.0",
        "Residential + Commercial Percent of Total": "5.363081548678422"
    },
    {
        "": "2",
        "Species": "Sulphur Dioxide",
        "Industrial": "13.47725002081582",
        "Onroad Transportation": "2.407961584739179",
        "Power": "0.8406970398886265",
        "Nonroad Transportation": "0.21675984574149215",
        "Other": "0.0",
        "Residential + Commercial": "2.39156412206426",
        "Industrial Percent of Total": "34.853335374954455",
        "Onroad Transportation Percent of Total": "6.22719713244892",
        "Power Percent of Total": "2.1741153302575653",
        "Nonroad Transportation Percent of Total": "0.5605597275247627",
        "Other Percent of Total": "0.0",
        "Residential + Commercial Percent of Total": "6.1847918743269314"
    },
    {
        "": "3",
        "Species": "Nitrogen Oxides",
        "Industrial": "215.49669541474054",
        "Onroad Transportation": "448.9066422150421",
        "Power": "78.76455874861459",
        "Nonroad Transportation": "111.24880928277268",
        "Other": "0.0",
        "Residential + Commercial": "40.503298656576376",
        "Industrial Percent of Total": "12.03999758272159",
        "Onroad Transportation Percent of Total": "25.080824913508476",
        "Power Percent of Total": "4.400647977976298",
        "Nonroad Transportation Percent of Total": "6.215572782995063",
        "Other Percent of Total": "0.0",
        "Residential + Commercial Percent of Total": "2.2629563621794313"
    },
    {
        "": "4",
        "Species": "Particulate Matter (PM2.5)",
        "Industrial": "79.24648425785333",
        "Onroad Transportation": "19.036156373477063",
        "Power": "3.5426015760713687",
        "Nonroad Transportation": "6.779086414818848",
        "Other": "177.71607532375816",
        "Residential + Commercial": "41.409546692861845",
        "Industrial Percent of Total": "12.090210777185865",
        "Onroad Transportation Percent of Total": "2.9042442084110474",
        "Power Percent of Total": "0.5404757088646385",
        "Nonroad Transportation Percent of Total": "1.0342488300835229",
        "Other Percent of Total": "27.11318778719886",
        "Residential + Commercial Percent of Total": "6.317632288587049"
    }
]