[
    {
        "YEAR": "2013",
        "Industry": "119695.29302133333",
        "Commercial": "995773.7138799999",
        "Onroad": "2000706.5604533332",
        "Railroad": "16499.594169666667",
        "Power": "435708.37309999997",
        "Aviation": "353656.0920566667",
        "Residential": "1180995.4112"
    },
    {
        "YEAR": "2014",
        "Industry": "110791.758957",
        "Commercial": "1047166.3757133334",
        "Onroad": "1884875.9362033333",
        "Railroad": "24940.738746",
        "Power": "358830.6825033333",
        "Aviation": "422552.0794",
        "Residential": "1304372.4096333333"
    },
    {
        "YEAR": "2015",
        "Industry": "120126.38030799999",
        "Commercial": "1046132.8405366666",
        "Onroad": "1976758.6258566666",
        "Railroad": "30275.29960033333",
        "Power": "379870.1049",
        "Aviation": "432936.8380333333",
        "Residential": "1297927.5862666667"
    },
    {
        "YEAR": "2016",
        "Industry": "106120.22384333334",
        "Commercial": "1016566.4254533333",
        "Onroad": "2077888.5257899999",
        "Railroad": "40558.19951333333",
        "Power": "403838.2461666667",
        "Aviation": "567719.4130666666",
        "Residential": "1100638.6310333335"
    },
    {
        "YEAR": "2017",
        "Industry": "115708.12593633332",
        "Commercial": "1064127.07676",
        "Onroad": "2050066.24086",
        "Railroad": "17134.316110999996",
        "Power": "456538.3977",
        "Aviation": "567719.4130666666",
        "Residential": "1194241.2423333332"
    },
    {
        "YEAR": "2018",
        "Industry": "108490.00704299999",
        "Commercial": "1145925.2692066666",
        "Onroad": "2069893.0496566668",
        "Railroad": "31158.538037000002",
        "Power": "575178.0551",
        "Aviation": "603292.4410333333",
        "Residential": "1288356.3649"
    },
    {
        "YEAR": "2019",
        "Industry": "110153.64911833333",
        "Commercial": "1175304.9468966667",
        "Onroad": "2003626.53062",
        "Railroad": "22761.93319033333",
        "Power": "558401.8197999999",
        "Aviation": "635205.6087666666",
        "Residential": "1320561.8792666665"
    },
    {
        "YEAR": "2020",
        "Industry": "104991.9519",
        "Commercial": "1053009.3652833335",
        "Onroad": "1657373.8000233332",
        "Railroad": "43543.202156666666",
        "Power": "610124.8545333333",
        "Aviation": "336780.66004",
        "Residential": "1142066.5358666666"
    },
    {
        "YEAR": "2021",
        "Industry": "110949.266714",
        "Commercial": "1098303.2337933332",
        "Onroad": "1752501.2017333333",
        "Railroad": "44441.80532",
        "Power": "383558.43386666663",
        "Aviation": "421994.65586666664",
        "Residential": "1175449.0396"
    }
]